xaal/__init__.py
xaal/alexa/__init__.py
xaal/alexa/__main__.py
xaal/alexa/devices.py
xaal/alexa/gw.py
xaal_alexa-0.1.2.dist-info/METADATA
xaal_alexa-0.1.2.dist-info/WHEEL
xaal_alexa-0.1.2.dist-info/top_level.txt
xaal_alexa-0.1.2.dist-info/RECORD
